{"name":"ingreso exitoso","id":"automatizar-el-login-y-carrito-de-compra-de-demoblaze;ingreso-exitoso","scenarioId":"demoblaze:ingreso exitoso","methodName":"ingreso exitoso","testSteps":[{"number":1,"description":"Dado que luisa ingresa a demoblaze","duration":7875,"startTime":"2024-04-18T14:59:54.824396-05:00[America/Bogota]","screenshots":[{"screenshot":"0a700f528ae5b6e409eb9d2913795fc196bcdd269355f4486cfb4010abb56ce0.png","timeStamp":1713470402698,"screenshotName":"0a700f528ae5b6e409eb9d2913795fc196bcdd269355f4486cfb4010abb56ce0.png"}],"result":"SUCCESS","precondition":false,"level":0,"children":[{"number":2,"description":"Luisa openup","duration":6503,"startTime":"2024-04-18T14:59:55.310152-05:00[America/Bogota]","screenshots":[{"screenshot":"0a700f528ae5b6e409eb9d2913795fc196bcdd269355f4486cfb4010abb56ce0.png","timeStamp":1713470401813,"screenshotName":"0a700f528ae5b6e409eb9d2913795fc196bcdd269355f4486cfb4010abb56ce0.png"}],"result":"SUCCESS","precondition":false,"level":1,"children":[{"number":3,"description":"luisa opens the Demoblaze page","duration":4851,"startTime":"2024-04-18T14:59:55.355544-05:00[America/Bogota]","screenshots":[{"screenshot":"5f5b348dd65c2bf788bf2c275c49db6e1d9acce6e643e61c4849b6019c481580.png","timeStamp":1713470400206,"screenshotName":"5f5b348dd65c2bf788bf2c275c49db6e1d9acce6e643e61c4849b6019c481580.png"}],"result":"SUCCESS","precondition":false,"level":2},{"number":4,"description":"luisa maximizes the browser","duration":1563,"startTime":"2024-04-18T15:00:00.220440-05:00[America/Bogota]","screenshots":[{"screenshot":"0a700f528ae5b6e409eb9d2913795fc196bcdd269355f4486cfb4010abb56ce0.png","timeStamp":1713470401783,"screenshotName":"0a700f528ae5b6e409eb9d2913795fc196bcdd269355f4486cfb4010abb56ce0.png"}],"result":"SUCCESS","precondition":false,"level":2}]}]},{"number":5,"description":"Cuando inicia sesion","duration":4492,"startTime":"2024-04-18T15:00:02.703308-05:00[America/Bogota]","screenshots":[{"screenshot":"089579002827d1f416caf912ac4ef264ec075e9aa50d51212cad2f3d5aa1acf0.png","timeStamp":1713470407195,"screenshotName":"089579002827d1f416caf912ac4ef264ec075e9aa50d51212cad2f3d5aa1acf0.png"}],"result":"SUCCESS","precondition":false,"level":0,"children":[{"number":6,"description":"Luisa login","duration":3690,"startTime":"2024-04-18T15:00:02.737501-05:00[America/Bogota]","screenshots":[{"screenshot":"eee0ffff89db7d314cec901b603300d9f1e143e8e26f249741130ed29542ddea.png","timeStamp":1713470406427,"screenshotName":"eee0ffff89db7d314cec901b603300d9f1e143e8e26f249741130ed29542ddea.png"}],"result":"SUCCESS","precondition":false,"level":1,"children":[{"number":7,"description":"luisa clicks on boton login","duration":1260,"startTime":"2024-04-18T15:00:02.823857-05:00[America/Bogota]","screenshots":[{"screenshot":"438017abc2a254279715f3abe1791b086cf18d901803a38b208b0f0d359eda2a.png","timeStamp":1713470404084,"screenshotName":"438017abc2a254279715f3abe1791b086cf18d901803a38b208b0f0d359eda2a.png"}],"result":"SUCCESS","precondition":false,"level":2},{"number":8,"description":"luisa enters \u0027andres\u0027 into campo usuario","duration":903,"startTime":"2024-04-18T15:00:04.086711-05:00[America/Bogota]","screenshots":[{"screenshot":"9079af149d8caffd5c0b1341edeabb886685db3a19dd0f1c80426aae7e391660.png","timeStamp":1713470404989,"screenshotName":"9079af149d8caffd5c0b1341edeabb886685db3a19dd0f1c80426aae7e391660.png"}],"result":"SUCCESS","precondition":false,"level":2},{"number":9,"description":"luisa enters \u0027andres\u0027 into campo contraseña","duration":550,"startTime":"2024-04-18T15:00:04.991536-05:00[America/Bogota]","screenshots":[{"screenshot":"d4a400146bf9e9ecf8a06a4fc9fd2c9d1943b7af4fdc2b399cdcc3aa5d5c4940.png","timeStamp":1713470405541,"screenshotName":"d4a400146bf9e9ecf8a06a4fc9fd2c9d1943b7af4fdc2b399cdcc3aa5d5c4940.png"}],"result":"SUCCESS","precondition":false,"level":2},{"number":10,"description":"luisa clicks on boton log in","duration":854,"startTime":"2024-04-18T15:00:05.542770-05:00[America/Bogota]","screenshots":[{"screenshot":"eee0ffff89db7d314cec901b603300d9f1e143e8e26f249741130ed29542ddea.png","timeStamp":1713470406397,"screenshotName":"eee0ffff89db7d314cec901b603300d9f1e143e8e26f249741130ed29542ddea.png"}],"result":"SUCCESS","precondition":false,"level":2}]}]},{"number":11,"description":"Entonces Verifico que inicio correctamente","duration":7,"startTime":"2024-04-18T15:00:07.196624-05:00[America/Bogota]","screenshots":[{"screenshot":"089579002827d1f416caf912ac4ef264ec075e9aa50d51212cad2f3d5aa1acf0.png","timeStamp":1713470407203,"screenshotName":"089579002827d1f416caf912ac4ef264ec075e9aa50d51212cad2f3d5aa1acf0.png"}],"result":"SUCCESS","precondition":false,"level":0}],"userStory":{"id":"demoblaze","storyName":"automatizar el login y carrito de compra de demoblaze","displayName":"automatizar el login y carrito de compra de demoblaze","path":"demoblaze","pathElements":[{"name":"demoblaze","description":""}],"narrative":"    Como un usuario quiero ingresar a demoblaze para comprar productos de la tienda","type":"feature"},"title":"ingreso exitoso","description":"","tags":[{"name":"Chrome","type":"context","displayName":"Chrome"},{"name":"Regresion","type":"tag","displayName":"Regresion"},{"name":"Mac","type":"context","displayName":"Mac"},{"name":"caso1","type":"tag","displayName":"caso1"},{"name":"Chrome, Mac","type":"context","displayName":"Chrome, Mac"}],"startTime":"2024-04-18T14:59:54.746937-05:00[America/Bogota]","duration":4477,"projectKey":"","sessionId":"d17f9d80cbf362076c78eb5ec29ee17b","driver":"chrome:luisa","isManualTestingUpToDate":false,"context":"chrome,mac","manual":false,"testSource":"Cucumber","actors":[{"name":"luisa","can":["browse the web"]}],"order":0,"result":"SUCCESS"}